README
setup.cfg
setup.py
okaara/__init__.py
okaara/cli.py
okaara/extensions.py
okaara/parsers.py
okaara/progress.py
okaara/prompt.py
okaara/shell.py
okaara/table.py
okaara/validators.py
okaara.egg-info/PKG-INFO
okaara.egg-info/SOURCES.txt
okaara.egg-info/dependency_links.txt
okaara.egg-info/requires.txt
okaara.egg-info/top_level.txt
test/test_cli.py
test/test_extensions.py
test/test_parsers.py
test/test_prompt.py
test/test_table.py
test/test_validators.py