Metadata-Version: 1.1
Name: okaara
Version: 1.0.37
Summary: Python command line utilities
Home-page: https://okaara.readthedocs.org/en/latest/
Author: Jay Dobies
Author-email: jdobies@gmail.com
License: GPLv2
Platform: UNKNOWN
Classifier: License :: OSI Approved :: GNU General Public License (GPL)
Classifier: Intended Audience :: Developers
Classifier: Intended Audience :: Information Technology
Classifier: Programming Language :: Python
